{
	"nav": [
		{
			"label": "Dashboard",
			"url": "/index.php"
		},

		{
			"label": "Pages",
			"url": "/posts/?type=page",

			"child": [{
					"label": "Add page",
					"url": "/pages/add.php?type=page"
				},
				{
					"label": "Edit pages",
					"url": "/pages/?type=page"
				}
			]
		},

		{
			"label": "News",
			"url": "/posts/?type=post",

			"child": [{
					"label": "Add news",
					"url": "/pages/add.php?type=post"
				},
				{
					"label": "Edit news",
					"url": "/pages/?type=post"
				}
			]
		},

		{
			"label": "Uploads",
			"url": "/uploads/"
		},

		{
			"label": "Users",
			"url": "/users",

			"child": [{
					"label": "Add user",
					"url": "/users/add.php"
				},
				{
					"label": "Users",
					"url": "/users"
				}
			]
		},

		{
			"label": "Appearance",
			"url": "/appearance",

			"child": [
				{
					"label": "Menus",
					"url": "/appearance/menus"
				},
				{
					"label": "Theme",
					"url": "/appearance/theme"
				}
			]
		},

		{
			"label": "Settings",
			"url": "/settings",

			"child": [
				{
					"label": "General settings",
					"url": "/settings/general"
				},
				{
					"label": "Languages",
					"url": "/settings/languages"
				},
				{
					"label": "Administrators",
					"url": "/settings/admins"
				},
				{
					"label": "Site structure",
					"url": "/settings/structure"
				}
			]
		}
	]
}